{
  "jsonapi": {
    "version": "1.0",
    "meta": {
      "links": {
        "self": {
          "href": "http://jsonapi.org/format/1.0/"
        }
      }
    }
  },
  "data": [
    {
      "type": "node--urgent_banner",
      "id": "2c562bbb-b00e-47f3-a170-5d0dbb87882b",
      "links": {
        "self": {
          "href": "https://mock-api.local/jsonapi/prison/wayland/node/urgent_banner/2c562bbb-b00e-47f3-a170-5d0dbb87882b?resourceVersion=id%3A64817"
        }
      },
      "attributes": {
        "drupal_internal__nid": 18631,
        "title": "Urgent update - This is a test update whilst we work on this functionality",
        "created": "2022-08-23T13:21:13+00:00",
        "changed": "2022-08-23T13:23:10+00:00"
      },
      "relationships": {
        "field_more_info_page": {
          "data": {
            "type": "node--page",
            "id": "82e03a3e-76e2-4d96-ac68-5c871f719177",
            "meta": {
              "drupal_internal__target_id": 7181
            }
          },
          "links": {
            "related": {
              "href": "https://mock-api.local/jsonapi/prison/wayland/node/urgent_banner/2c562bbb-b00e-47f3-a170-5d0dbb87882b/field_more_info_page?resourceVersion=id%3A64817"
            },
            "self": {
              "href": "https://mock-api.local/jsonapi/prison/wayland/node/urgent_banner/2c562bbb-b00e-47f3-a170-5d0dbb87882b/relationships/field_more_info_page?resourceVersion=id%3A64817"
            }
          }
        }
      }
    },
    {
      "type": "node--urgent_banner",
      "id": "24f2974e-c72a-4921-8c49-413e48a1fc41",
      "links": {
        "self": {
          "href": "https://mock-api.local/jsonapi/prison/wayland/node/urgent_banner/24f2974e-c72a-4921-8c49-413e48a1fc41?resourceVersion=id%3A64818"
        }
      },
      "attributes": {
        "drupal_internal__nid": 18632,
        "title": "Urgent update - This is another test update whilst we work on this functionality (with no more info link)",
        "created": "2022-08-23T13:23:24+00:00",
        "changed": "2022-08-23T13:23:47+00:00"
      },
      "relationships": {
        "field_more_info_page": {
          "data": null,
          "links": {
            "related": {
              "href": "https://mock-api.local/jsonapi/prison/wayland/node/urgent_banner/24f2974e-c72a-4921-8c49-413e48a1fc41/field_more_info_page?resourceVersion=id%3A64818"
            },
            "self": {
              "href": "https://mock-api.local/jsonapi/prison/wayland/node/urgent_banner/24f2974e-c72a-4921-8c49-413e48a1fc41/relationships/field_more_info_page?resourceVersion=id%3A64818"
            }
          }
        }
      }
    }
  ],
  "included": [
    {
      "type": "node--page",
      "id": "82e03a3e-76e2-4d96-ac68-5c871f719177",
      "links": {
        "self": {
          "href": "https://mock-api.local/jsonapi/prison/wayland/node/page/82e03a3e-76e2-4d96-ac68-5c871f719177?resourceVersion=id%3A63238"
        }
      },
      "attributes": {
        "drupal_internal__nid": 7181,
        "title": "FYI: Vitamin D",
        "created": "2020-11-13T12:40:16+00:00",
        "breadcrumbs": [
          {
            "uri": "/",
            "title": "Home",
            "options": []
          },
          {
            "uri": "/tags/644",
            "title": "News and events",
            "options": []
          },
          {
            "uri": "/tags/1394",
            "title": "FYI: Information in Wayland",
            "options": []
          }
        ],
        "field_exclude_feedback": false,
        "field_moj_description": {
          "value": "<p>&nbsp;</p>\r\n\r\n<p><a href=\"/content/7183\">HMPPS Question and Answers&nbsp;about vitamin D</a></p>\r\n\r\n<p><a href=\"/content/7180\">Information from the NHS website&nbsp;about vitamin D</a></p>\r\n\r\n<p><img alt=\"Vitamin D Poster\" data-align=\"left\" data-entity-type=\"file\" data-entity-uuid=\"0e832cd6-0519-4539-8efa-2d7ff98d56d0\" height=\"1396\" src=\"https://cloud-platform-5e5f7ac99afe21a0181cbf50a850627b.s3.eu-west-1.amazonaws.com/inline-images/Screenshot%202020-11-13%20at%2012.45.50.png?X-Amz-Content-Sha256=UNSIGNED-PAYLOAD&amp;X-Amz-Algorithm=AWS4-HMAC-SHA256&amp;X-Amz-Credential=AKIA27HJSWAHOEAPZ56S%2F20220804%2Feu-west-1%2Fs3%2Faws4_request&amp;X-Amz-Date=20220804T151422Z&amp;X-Amz-SignedHeaders=host&amp;X-Amz-Expires=38738&amp;X-Amz-Signature=1ceff029c5f497eef618d82c0558f0f8785d1a9f61b6d064c86468f9f1f10001\" width=\"990\" /></p>\r\n",
          "format": "basic_html",
          "processed": "<p> </p>\n\n<p><a href=\"/content/7183\">HMPPS Question and Answers about vitamin D</a></p>\n\n<p><a href=\"/content/7180\">Information from the NHS website about vitamin D</a></p>\n\n<p><img alt=\"Vitamin D Poster\" data-entity-type=\"file\" data-entity-uuid=\"0e832cd6-0519-4539-8efa-2d7ff98d56d0\" height=\"1396\" src=\"https://cloud-platform-c3b3fc90408e8f9501268e354d44f461.s3.eu-west-2.amazonaws.com/inline-images/Screenshot%202020-11-13%20at%2012.45.50.png?X-Amz-Content-Sha256=UNSIGNED-PAYLOAD&amp;X-Amz-Algorithm=AWS4-HMAC-SHA256&amp;X-Amz-Credential=AKIA27HJSWAHLQIQVZEJ%2F20220901%2Feu-west-2%2Fs3%2Faws4_request&amp;X-Amz-Date=20220901T061437Z&amp;X-Amz-SignedHeaders=host&amp;X-Amz-Expires=71123&amp;X-Amz-Signature=acd3d2749b467077bf086f454c58e270cea7cdb45e61f606b4f2bc1518ca548c\" width=\"990\" class=\"align-left\" loading=\"lazy\" /></p>",
          "summary": "Information about the benefits of vitamin D and you can access it."
        },
        "field_moj_stand_first": "Your body needs vitamin D. From 1 March you can order vitamin D on canteen forms – free of charge. ",
        "drupal_internal__vid": 63238,
        "langcode": "en",
        "revision_timestamp": "2022-08-04T15:14:34+00:00",
        "revision_log": null,
        "status": true,
        "changed": "2022-08-04T15:14:34+00:00",
        "promote": false,
        "sticky": false,
        "default_langcode": true,
        "revision_translation_affected": true,
        "path": {
          "alias": "/content/7181",
          "pid": 2872,
          "langcode": "en"
        },
        "series_sort_value": -1614168000,
        "publish_on": null,
        "unpublish_on": null,
        "published_at": "2020-11-13T12:50:07+00:00",
        "field_moj_episode": null,
        "field_moj_season": null,
        "field_release_date": null
      },
      "relationships": {
        "field_moj_series": {
          "data": null,
          "links": {
            "related": {
              "href": "https://mock-api.local/jsonapi/prison/wayland/node/page/82e03a3e-76e2-4d96-ac68-5c871f719177/field_moj_series?resourceVersion=id%3A63238"
            },
            "self": {
              "href": "https://mock-api.local/jsonapi/prison/wayland/node/page/82e03a3e-76e2-4d96-ac68-5c871f719177/relationships/field_moj_series?resourceVersion=id%3A63238"
            }
          }
        },
        "field_moj_top_level_categories": {
          "data": {
            "type": "taxonomy_term--moj_categories",
            "id": "91b023c9-fb03-422c-9f70-3c7a5da0e2ff",
            "meta": {
              "drupal_internal__target_id": 1394
            }
          },
          "links": {
            "related": {
              "href": "https://mock-api.local/jsonapi/prison/wayland/node/page/82e03a3e-76e2-4d96-ac68-5c871f719177/field_moj_top_level_categories?resourceVersion=id%3A63238"
            },
            "self": {
              "href": "https://mock-api.local/jsonapi/prison/wayland/node/page/82e03a3e-76e2-4d96-ac68-5c871f719177/relationships/field_moj_top_level_categories?resourceVersion=id%3A63238"
            }
          }
        },
        "field_topics": {
          "data": [],
          "links": {
            "related": {
              "href": "https://mock-api.local/jsonapi/prison/wayland/node/page/82e03a3e-76e2-4d96-ac68-5c871f719177/field_topics?resourceVersion=id%3A63238"
            },
            "self": {
              "href": "https://mock-api.local/jsonapi/prison/wayland/node/page/82e03a3e-76e2-4d96-ac68-5c871f719177/relationships/field_topics?resourceVersion=id%3A63238"
            }
          }
        },
        "node_type": {
          "data": {
            "type": "node_type--node_type",
            "id": "2a0fd1a2-181b-4638-b6f0-9356b1a84dca",
            "meta": {
              "drupal_internal__target_id": "page"
            }
          },
          "links": {
            "related": {
              "href": "https://mock-api.local/jsonapi/prison/wayland/node/page/82e03a3e-76e2-4d96-ac68-5c871f719177/node_type?resourceVersion=id%3A63238"
            },
            "self": {
              "href": "https://mock-api.local/jsonapi/prison/wayland/node/page/82e03a3e-76e2-4d96-ac68-5c871f719177/relationships/node_type?resourceVersion=id%3A63238"
            }
          }
        },
        "revision_uid": {
          "data": {
            "type": "user--user",
            "id": "5dba7612-5f74-41e3-9022-781214f2fa4c",
            "meta": {
              "drupal_internal__target_id": 975
            }
          },
          "links": {
            "related": {
              "href": "https://mock-api.local/jsonapi/prison/wayland/node/page/82e03a3e-76e2-4d96-ac68-5c871f719177/revision_uid?resourceVersion=id%3A63238"
            },
            "self": {
              "href": "https://mock-api.local/jsonapi/prison/wayland/node/page/82e03a3e-76e2-4d96-ac68-5c871f719177/relationships/revision_uid?resourceVersion=id%3A63238"
            }
          }
        },
        "uid": {
          "data": {
            "type": "user--user",
            "id": "65af138a-aa71-4197-99aa-df114ea3c108",
            "meta": {
              "drupal_internal__target_id": 278
            }
          },
          "links": {
            "related": {
              "href": "https://mock-api.local/jsonapi/prison/wayland/node/page/82e03a3e-76e2-4d96-ac68-5c871f719177/uid?resourceVersion=id%3A63238"
            },
            "self": {
              "href": "https://mock-api.local/jsonapi/prison/wayland/node/page/82e03a3e-76e2-4d96-ac68-5c871f719177/relationships/uid?resourceVersion=id%3A63238"
            }
          }
        },
        "field_exclude_from_prison": {
          "data": [],
          "links": {
            "related": {
              "href": "https://mock-api.local/jsonapi/prison/wayland/node/page/82e03a3e-76e2-4d96-ac68-5c871f719177/field_exclude_from_prison?resourceVersion=id%3A63238"
            },
            "self": {
              "href": "https://mock-api.local/jsonapi/prison/wayland/node/page/82e03a3e-76e2-4d96-ac68-5c871f719177/relationships/field_exclude_from_prison?resourceVersion=id%3A63238"
            }
          }
        },
        "field_moj_secondary_tags": {
          "data": [],
          "links": {
            "related": {
              "href": "https://mock-api.local/jsonapi/prison/wayland/node/page/82e03a3e-76e2-4d96-ac68-5c871f719177/field_moj_secondary_tags?resourceVersion=id%3A63238"
            },
            "self": {
              "href": "https://mock-api.local/jsonapi/prison/wayland/node/page/82e03a3e-76e2-4d96-ac68-5c871f719177/relationships/field_moj_secondary_tags?resourceVersion=id%3A63238"
            }
          }
        },
        "field_moj_thumbnail_image": {
          "data": {
            "type": "file--file",
            "id": "7b644727-f615-4d08-8511-0821b38a3440",
            "meta": {
              "alt": "Vitamin D in prison",
              "title": "",
              "width": 990,
              "height": 1396,
              "drupal_internal__target_id": 18730
            }
          },
          "links": {
            "related": {
              "href": "https://mock-api.local/jsonapi/prison/wayland/node/page/82e03a3e-76e2-4d96-ac68-5c871f719177/field_moj_thumbnail_image?resourceVersion=id%3A63238"
            },
            "self": {
              "href": "https://mock-api.local/jsonapi/prison/wayland/node/page/82e03a3e-76e2-4d96-ac68-5c871f719177/relationships/field_moj_thumbnail_image?resourceVersion=id%3A63238"
            }
          }
        },
        "field_prisons": {
          "data": [
            {
              "type": "taxonomy_term--prisons",
              "id": "b73767ea-2cbb-4ad5-ba22-09379cc07241",
              "meta": {
                "drupal_internal__target_id": 793
              }
            }
          ],
          "links": {
            "related": {
              "href": "https://mock-api.local/jsonapi/prison/wayland/node/page/82e03a3e-76e2-4d96-ac68-5c871f719177/field_prisons?resourceVersion=id%3A63238"
            },
            "self": {
              "href": "https://mock-api.local/jsonapi/prison/wayland/node/page/82e03a3e-76e2-4d96-ac68-5c871f719177/relationships/field_prisons?resourceVersion=id%3A63238"
            }
          }
        },
        "field_prison_owner": {
          "data": [
            {
              "type": "taxonomy_term--prisons",
              "id": "b73767ea-2cbb-4ad5-ba22-09379cc07241",
              "meta": {
                "drupal_internal__target_id": 793
              }
            }
          ],
          "links": {
            "related": {
              "href": "https://mock-api.local/jsonapi/prison/wayland/node/page/82e03a3e-76e2-4d96-ac68-5c871f719177/field_prison_owner?resourceVersion=id%3A63238"
            },
            "self": {
              "href": "https://mock-api.local/jsonapi/prison/wayland/node/page/82e03a3e-76e2-4d96-ac68-5c871f719177/relationships/field_prison_owner?resourceVersion=id%3A63238"
            }
          }
        }
      }
    }
  ],
  "links": {
    "self": {
      "href": "https://mock-api.local/jsonapi/prison/wayland/node/urgent_banner?fields%5Bnode--urgent_banner%5D=drupal_internal__nid%2Ctitle%2Ccreated%2Cchanged%2Cfield_more_info_page&include=field_more_info_page"
    }
  }
}
